ploosh/__init__.py
ploosh/__main__.py
ploosh/case.py
ploosh/configuration.py
ploosh/execute.py
ploosh/logs.py
ploosh/parameters.py
ploosh/version.py
ploosh/connectors/__init__.py
ploosh/connectors/connector.py
ploosh/connectors/connector_analysis_services.py
ploosh/connectors/connector_bigquery.py
ploosh/connectors/connector_csv.py
ploosh/connectors/connector_csv_spark.py
ploosh/connectors/connector_databricks.py
ploosh/connectors/connector_delta.py
ploosh/connectors/connector_delta_spark.py
ploosh/connectors/connector_empty.py
ploosh/connectors/connector_empty_spark.py
ploosh/connectors/connector_excel.py
ploosh/connectors/connector_fabric_kql_spark.py
ploosh/connectors/connector_json.py
ploosh/connectors/connector_json_spark.py
ploosh/connectors/connector_mssql.py
ploosh/connectors/connector_mysql.py
ploosh/connectors/connector_odbc.py
ploosh/connectors/connector_parquet.py
ploosh/connectors/connector_parquet_spark.py
ploosh/connectors/connector_postgresql.py
ploosh/connectors/connector_semantic_model_xmla.py
ploosh/connectors/connector_snowflake.py
ploosh/connectors/connector_sql_spark.py
ploosh/engines/compare_engine.py
ploosh/engines/compare_engine_native.py
ploosh/engines/compare_engine_spark.py
ploosh/engines/load_engine.py
ploosh/engines/load_engine_native.py
ploosh/engines/load_engine_spark.py
ploosh/exporters/__init__.py
ploosh/exporters/exporter.py
ploosh/exporters/exporter_csv.py
ploosh/exporters/exporter_json.py
ploosh/exporters/exporter_trx.py
ploosh_core-0.4.7.dist-info/METADATA
ploosh_core-0.4.7.dist-info/WHEEL
ploosh_core-0.4.7.dist-info/entry_points.txt
ploosh_core-0.4.7.dist-info/top_level.txt
ploosh_core-0.4.7.dist-info/RECORD
