Metadata-Version: 2.1
Name: ploosh-core
Version: 0.4.7
Summary: A framework to automatize your tests for data projects
Home-page: https://github.com/CSharplie/ploosh/
Download-URL: https://pypi.org/project/ploosh/
License: Apache License 2.0
Project-URL: Say Thanks!, https://ploosh.io
Project-URL: Bug Tracker, https://github.com/CSharplie/ploosh/issues
Project-URL: CI, https://github.com/CSharplie/ploosh/actions
Project-URL: Documentation, https://ploosh.io/docs/ploosh/
Project-URL: Source Code, https://github.com/CSharplie/ploosh
Platform: Any
Requires-Python: >=3.6
Requires-Dist: colorama==0.4.6
Requires-Dist: PyYAML==6.0.1
Requires-Dist: Pyjeb==0.2.1
Requires-Dist: numpy==1.26.3
Requires-Dist: pandas==2.1.4
Requires-Dist: openpyxl==3.1.2
Requires-Dist: sqlalchemy==1.4.51
Requires-Dist: pyspark==3.5.4
Requires-Dist: deltalake==0.23.2
Requires-Dist: delta-spark==3.3.0
Requires-Dist: pyarrow==18.0.0
